{"url":"https:\/\/lombardd.bitrix24.ru\/rest\/1\/jbni1ickgwzjtym0\/crm.lead.add.json","info":{"url":"https:\/\/lombardd.bitrix24.ru\/rest\/1\/jbni1ickgwzjtym0\/crm.lead.add.json","content_type":"application\/json; charset=utf-8","http_code":"200","header_size":"1156","request_size":"673","filetime":"-1","ssl_verify_result":"0","redirect_count":"0","total_time":"0.446621","namelookup_time":"0.060479","connect_time":"0.062459","pretransfer_time":"0.079747","size_upload":"502","size_download":"226","speed_download":"506","speed_upload":"1123","download_content_length":"-1","upload_content_length":"502","starttransfer_time":"0.446589","redirect_time":"0","redirect_url":"","primary_ip":"46.235.53.69","certinfo":[],"primary_port":"443","local_ip":"172.17.0.68","local_port":"55396"},"params":{"method":"crm.lead.add","params":{"fields":{"UF_CRM_1589030693":"588325","UF_CRM_1589031190":"https:\/\/lombardd.ru\/data\/isdelia-iz-serebra\/skupka-serebra-925-proby\/","TITLE":"\u041f\u043e\u043b\u0443\u0447\u0438\u0442\u044c \u0437\u0430\u0439\u043c","NAME":"\u041c\u0438\u0440\u0430\u0441","STATUS_ID":"4","OPENED":"Y","ASSIGNED_BY_ID":"1","PHONE":[{"VALUE":"8 (708)644-80-59","VALUE_TYPE":"HOME"}]},"params":{"REGISTER_SONET_EVENT":"Y"}}},"result":{"result":"79114","time":{"start":"1630172178.4411","finish":"1630172178.7666","duration":"0.3255078792572","processing":"0.30109691619873","date_start":"2021-08-28T20:36:18+03:00","date_finish":"2021-08-28T20:36:18+03:00"}}}