{"url":"https:\/\/lombardd.bitrix24.ru\/rest\/1\/jbni1ickgwzjtym0\/crm.lead.add.json","info":{"url":"https:\/\/lombardd.bitrix24.ru\/rest\/1\/jbni1ickgwzjtym0\/crm.lead.add.json","content_type":"application\/json; charset=utf-8","http_code":"200","header_size":"1179","request_size":"734","filetime":"-1","ssl_verify_result":"0","redirect_count":"0","total_time":"1.194443","namelookup_time":"0.06913","connect_time":"0.087012","pretransfer_time":"0.177125","size_upload":"563","size_download":"226","speed_download":"189","speed_upload":"471","download_content_length":"-1","upload_content_length":"563","starttransfer_time":"1.194305","redirect_time":"0","redirect_url":"","primary_ip":"178.132.201.50","certinfo":[],"primary_port":"443","local_ip":"172.17.0.68","local_port":"37576"},"params":{"method":"crm.lead.add","params":{"fields":{"UF_CRM_1589030693":"306646","UF_CRM_1589031190":"https:\/\/lombardd.ru\/?utm_source=yandex\u0026utm_medium=cpd\u0026utm_campaign=maps\u0026utm_term=knopka_deistvia","TITLE":"\u0417\u0430\u043a\u0430\u0437\u0430\u0442\u044c \u0437\u0432\u043e\u043d\u043e\u043a","NAME":"\u0422\u0430\u0442\u044c\u044f\u043d\u0430","STATUS_ID":"4","OPENED":"Y","ASSIGNED_BY_ID":"1","PHONE":[{"VALUE":"8 (926)583-80-83","VALUE_TYPE":"HOME"}]},"params":{"REGISTER_SONET_EVENT":"Y"}}},"result":{"result":"25868","time":{"start":"1606483142.7344","finish":"1606483143.643","duration":"0.90859007835388","processing":"0.82819986343384","date_start":"2020-11-27T16:19:02+03:00","date_finish":"2020-11-27T16:19:03+03:00"}}}