{"url":"https:\/\/lombardd.bitrix24.ru\/rest\/1\/jbni1ickgwzjtym0\/crm.lead.add.json","info":{"url":"https:\/\/lombardd.bitrix24.ru\/rest\/1\/jbni1ickgwzjtym0\/crm.lead.add.json","content_type":"application\/json; charset=utf-8","http_code":"200","header_size":"1168","request_size":"194","filetime":"-1","ssl_verify_result":"0","redirect_count":"0","total_time":"0.475752","namelookup_time":"0.060805","connect_time":"0.06301","pretransfer_time":"0.0934","size_upload":"1042","size_download":"225","speed_download":"472","speed_upload":"2190","download_content_length":"-1","upload_content_length":"1042","starttransfer_time":"0.097336","redirect_time":"0","redirect_url":"","primary_ip":"46.235.53.67","certinfo":[],"primary_port":"443","local_ip":"172.17.0.68","local_port":"53770"},"params":{"method":"crm.lead.add","params":{"fields":{"UF_CRM_1589030693":"389173","UF_CRM_1589031190":"https:\/\/lombardd.ru\/skupka-tekhniki\/smartfony\/?utm_source=yandex_direct\u0026utm_medium=cpc\u0026utm_campaign=lombard_search_department_search_57379803\u0026utm_term=%D0%BB%D0%BE%D0%BC%D0%B1%D0%B0%D1%80%D0%B4%20%D0%BF%D1%80%D0%BE%D1%81%D0%BF%D0%B5%D0%BA%D1%82%20%D0%B2%D0%B5%D1%80%D0%BD%D0%B0%D0%B4%D1%81%D0%BA%D0%BE%D0%B3%D0%BE\u0026cm_id=57379803_4389291068_9980220153_23984627074__none_search_type1_no_mobile_premium_213\u0026utm_content=9980220153\u0026yclid=232549312719530426","TITLE":"\u041e\u0441\u0442\u0430\u0432\u0438\u0442\u044c \u0437\u0430\u044f\u0432\u043a\u0443","NAME":"\u0410\u043b\u0435\u043a\u0441\u0435\u0439","STATUS_ID":"4","OPENED":"Y","ASSIGNED_BY_ID":"1","PHONE":[{"VALUE":"8 (977)597-59-66","VALUE_TYPE":"HOME"}]},"params":{"REGISTER_SONET_EVENT":"Y"}}},"result":{"result":"37828","time":{"start":"1611988044.2034","finish":"1611988044.5416","duration":"0.33818197250366","processing":"0.30528116226196","date_start":"2021-01-30T09:27:24+03:00","date_finish":"2021-01-30T09:27:24+03:00"}}}