{"url":"https:\/\/lombardd.bitrix24.ru\/rest\/1\/jbni1ickgwzjtym0\/crm.lead.add.json","info":{"url":"https:\/\/lombardd.bitrix24.ru\/rest\/1\/jbni1ickgwzjtym0\/crm.lead.add.json","content_type":"application\/json; charset=utf-8","http_code":"200","header_size":"1160","request_size":"635","filetime":"-1","ssl_verify_result":"0","redirect_count":"0","total_time":"0.95296","namelookup_time":"0.060847","connect_time":"0.07285","pretransfer_time":"0.114664","size_upload":"464","size_download":"225","speed_download":"236","speed_upload":"486","download_content_length":"-1","upload_content_length":"464","starttransfer_time":"0.952904","redirect_time":"0","redirect_url":"","primary_ip":"178.132.201.51","certinfo":[],"primary_port":"443","local_ip":"172.17.0.68","local_port":"46304"},"params":{"method":"crm.lead.add","params":{"fields":{"UF_CRM_1589030693":"490259","UF_CRM_1589031190":"https:\/\/lombardd.ru\/personal\/","TITLE":"\u0417\u0430\u043a\u0430\u0437\u0430\u0442\u044c \u0437\u0432\u043e\u043d\u043e\u043a","NAME":"\u0410\u043b\u043b\u0430","STATUS_ID":"4","OPENED":"Y","ASSIGNED_BY_ID":"1","PHONE":[{"VALUE":"8 (903)239-23-37","VALUE_TYPE":"HOME"}]},"params":{"REGISTER_SONET_EVENT":"Y"}}},"result":{"result":"53736","time":{"start":"1619071786.1537","finish":"1619071786.9165","duration":"0.76279211044312","processing":"0.71189904212952","date_start":"2021-04-22T09:09:46+03:00","date_finish":"2021-04-22T09:09:46+03:00"}}}