{"url":"https:\/\/lombardd.bitrix24.ru\/rest\/1\/jbni1ickgwzjtym0\/crm.lead.add.json","info":{"url":"https:\/\/lombardd.bitrix24.ru\/rest\/1\/jbni1ickgwzjtym0\/crm.lead.add.json","content_type":"application\/json; charset=utf-8","http_code":"200","header_size":"1164","request_size":"647","filetime":"-1","ssl_verify_result":"0","redirect_count":"0","total_time":"0.428193","namelookup_time":"0.004749","connect_time":"0.00867","pretransfer_time":"0.041827","size_upload":"476","size_download":"227","speed_download":"530","speed_upload":"1111","download_content_length":"-1","upload_content_length":"476","starttransfer_time":"0.427957","redirect_time":"0","redirect_url":"","primary_ip":"195.208.185.4","certinfo":[],"primary_port":"443","local_ip":"172.17.0.68","local_port":"54512"},"params":{"method":"crm.lead.add","params":{"fields":{"UF_CRM_1589030693":"459531","UF_CRM_1589031190":"https:\/\/lombardd.ru\/personal\/","TITLE":"\u0417\u0430\u043a\u0430\u0437\u0430\u0442\u044c \u0437\u0432\u043e\u043d\u043e\u043a","NAME":"\u0420\u0443\u0441\u043b\u0430\u043d","STATUS_ID":"4","OPENED":"Y","ASSIGNED_BY_ID":"1","PHONE":[{"VALUE":"8 (925)320-20-20","VALUE_TYPE":"HOME"}]},"params":{"REGISTER_SONET_EVENT":"Y"}}},"result":{"result":"49302","time":{"start":"1617126509.5568","finish":"1617126509.9","duration":"0.34325003623962","processing":"0.3130989074707","date_start":"2021-03-30T20:48:29+03:00","date_finish":"2021-03-30T20:48:29+03:00"}}}